ensure_import-0.6.2.dist-info/METADATA
ensure_import-0.6.2.dist-info/WHEEL
ensure_import-0.6.2.dist-info/entry_points.txt
ensure_import-0.6.2.dist-info/licenses/LICENSE
ensure_import/__init__.py
ensure_import/py.typed
ensure_import-0.6.2.dist-info/RECORD
