Metadata-Version: 2.1
Name: ensure-import
Version: 0.6.2
Summary: Auto install third part packages into virtual environment when import error.
Author-Email: Waket Zheng <waketzheng@gmail.com>
License: MIT
Project-URL: homepage, https://github.com/waketzheng/ensure_import
Requires-Python: >=3.10
